cart/__init__.py
cart/cart.py
cart/peeker.py
cart/version.py
cart-1.1.8.dist-info/LICENSE.md
cart-1.1.8.dist-info/METADATA
cart-1.1.8.dist-info/WHEEL
cart-1.1.8.dist-info/entry_points.txt
cart-1.1.8.dist-info/top_level.txt
cart-1.1.8.dist-info/RECORD
