Metadata-Version: 2.1
Name: cart
Version: 1.1.8
Summary: CaRT Neutering format
Home-page: https://bitbucket.org/cse-assemblyline/cart
Author: CSE-CST Assemblyline development team
Author-email: assemblyline@cyber.gc.ca
License: MIT
Keywords: neutering format malware cart stix development gc canada cse-cst cse cst cccs cyber
Platform: UNKNOWN
Classifier: Development Status :: 5 - Production/Stable
Classifier: Intended Audience :: Developers
Classifier: Topic :: Software Development :: Libraries
Classifier: License :: OSI Approved :: MIT License
Classifier: Programming Language :: Python :: 2
Classifier: Programming Language :: Python :: 2.7
Classifier: Programming Language :: Python :: 3
Classifier: Programming Language :: Python :: 3.6
Classifier: Programming Language :: Python :: 3.7
Classifier: Programming Language :: Python :: 3.8
Requires-Dist: pycryptodome
